brawlpython/__init__.py
brawlpython/api.py
brawlpython/api_toolkit.py
brawlpython/async_init.py
brawlpython/base_classes.py
brawlpython/cache_utils.py
brawlpython/clients.py
brawlpython/exceptions.py
brawlpython/experiments.py
brawlpython/optional_format.py
brawlpython/sessions.py
brawlpython/typedefs.py
brawlpython-2.6.0.dist-info/LICENSE
brawlpython-2.6.0.dist-info/METADATA
brawlpython-2.6.0.dist-info/WHEEL
brawlpython-2.6.0.dist-info/top_level.txt
brawlpython-2.6.0.dist-info/RECORD
