Metadata-Version: 2.1
Name: brawlpython
Version: 2.6.0
Summary: Easy-to-configure library to use Official and other Brawl Stars API
Home-page: https://github.com/0dminnimda/brawlpython
Author: 0dminnimda
Author-email: 0dminnimda.contact@gmail.com
License: MIT
Project-URL: Say Thanks!, https://saythanks.io/to/0dminnimda.contact%40gmail.com
Project-URL: Bug tracker, https://github.com/0dminnimda/brawlpython/issues
Project-URL: Code examples, https://github.com/0dminnimda/brawlpython/tree/master/examples
Keywords: brawl stars, brawl stars api, brawlstars,supercell, brawl, stars, api,brawlpython, python, async, aiohttp, sync, requests,
Platform: UNKNOWN
Classifier: Development Status :: 2 - Pre-Alpha
Classifier: Framework :: AsyncIO
Classifier: Intended Audience :: Developers
Classifier: License :: OSI Approved :: MIT License
Classifier: Operating System :: OS Independent
Classifier: Programming Language :: Python :: 3
Classifier: Programming Language :: Python :: 3.6
Classifier: Programming Language :: Python :: 3.7
Classifier: Programming Language :: Python :: 3.8
Classifier: Topic :: Games/Entertainment :: Real Time Strategy
Classifier: Topic :: Internet :: WWW/HTTP :: Session
Classifier: Topic :: Utilities
Classifier: Typing :: Typed
Requires-Python: ~=3.6
Requires-Dist: requests (~=2.24.0)
Requires-Dist: aiohttp (~=3.6.2)
Requires-Dist: cachetools (~=4.1.1)
Requires-Dist: pyformatting (~=0.2.1)
